pecos_rslib/__init__.pyi
pecos_rslib/__init__.py
pecos_rslib/pecos_rslib.abi3.so
pecos_rslib/py.typed
pecos_rslib/.dylibs/libc++abi.1.0.dylib
pecos_rslib/.dylibs/libunwind.1.0.dylib
pecos_rslib/.dylibs/libc++.1.0.dylib
pecos_rslib-0.8.0.dev0.dist-info/RECORD
pecos_rslib-0.8.0.dev0.dist-info/WHEEL
pecos_rslib-0.8.0.dev0.dist-info/METADATA
pecos_rslib-0.8.0.dev0.dist-info/licenses/LICENSE
