Metadata-Version: 2.4
Name: pecos-rslib
Version: 0.8.0.dev0
Classifier: Development Status :: 4 - Beta
Classifier: Intended Audience :: Developers
Classifier: Intended Audience :: Science/Research
Classifier: License :: OSI Approved :: Apache Software License
Classifier: Operating System :: OS Independent
Classifier: Topic :: Scientific/Engineering :: Physics
Classifier: Programming Language :: Python :: 3
Classifier: Programming Language :: Python :: 3.10
Classifier: Programming Language :: Python :: 3.11
Classifier: Programming Language :: Python :: 3.12
Classifier: Programming Language :: Python :: 3.13
Classifier: Programming Language :: Python :: 3.14
Classifier: Programming Language :: Python :: Implementation :: CPython
Classifier: Programming Language :: Rust
License-File: LICENSE
Summary: Rust libary extensions for Python PECOS.
Home-Page: https://pecos.io
Author: The PECOS Developers
Maintainer-email: Ciaran Ryan-Anderson <ciaranra@gmail.com>
License-Expression: Apache-2.0
Requires-Python: >=3.10
